{
    "appKeys": {},
    "capabilities": [
        ""
    ],
    "companyName": "kedar1916@gmail.com",
    "longName": "simply",
    "projectType": "simplyjs",
    "resources": {
        "media": [
            {
                "file": "menu_icon.png",
                "menuIcon": true,
                "name": "IMAGE_MENU_ICON",
                "type": "png"
            },
            {
                "file": "images/logo_splash.png",
                "name": "IMAGE_LOGO_SPLASH",
                "type": "png"
            },
            {
                "file": "fonts/UbuntuMono-Regular.ttf",
                "name": "MONO_FONT_14",
                "type": "font"
            }
        ]
    },
    "shortName": "simply",
    "uuid": "1eafb67f-e8c1-4804-a13b-3c9dd22b3e29",
    "versionCode": 1,
    "versionLabel": "1.0",
    "watchapp": {
        "watchface": false
    }
}
